drive_bot_proto/__init__.py
drive_bot_proto/client_pb2.py
drive_bot_proto/client_pb2.pyi
drive_bot_proto/client_pb2_grpc.py
drive_bot_proto/py.typed
drive_bot_proto-1.0.1.dist-info/METADATA
drive_bot_proto-1.0.1.dist-info/WHEEL
drive_bot_proto-1.0.1.dist-info/top_level.txt
drive_bot_proto-1.0.1.dist-info/RECORD
