Metadata-Version: 2.1
Name: drive-bot-proto
Version: 1.0.1
Summary: GRPC client for drive_bot_proto
Home-page: UNKNOWN
Author: Pavel Anokhin
Author-email: p.a.anokhin@gmail.com
License: UNKNOWN
Platform: UNKNOWN
